KolaViz/__init__.py
KolaViz/circuits.py
KolaViz/harmonisation_data.py
KolaViz/koNLP.py
KolaViz/koNMF.py
KolaViz/mlk_tokenizer.py
KolaViz/Lib/__init__.py
KolaViz/Lib/fnames.py
KolaViz/Lib/func4unige.py
KolaViz/Lib/mlkmtpgenerator.py
KolaViz/Lib/mlktypes.py
KolaViz/Lib/model.py
KolaViz/Lib/nlpDico.py
KolaViz/Lib/outilsKoNLP.py
KolaViz/Lib/tbutils.py
KolaViz/LibCircuits/__init__.py
KolaViz/LibCircuits/circuit_detector.py
KolaViz/LibCircuits/compute_seuil.py
KolaViz/LibCircuits/connexion.py
KolaViz/LibCircuits/dummyGraph.py
KolaViz/LibCircuits/network_utils.py
KolaViz/LibCircuits/temporal.py
KolaViz/LibCircuits/utilsCircuits2.py
KolaViz/LibCircuits/vertex_accessors.py
KolaViz/LibHD/__init__.py
KolaViz/LibHD/mlkdataprep.py
KolaViz/LibPlot/__init__.py
KolaViz/LibPlot/protodata.py
KolaViz/LibPlot/protograph.py
KolaViz-0.0.3.dist-info/LICENSE.txt
KolaViz-0.0.3.dist-info/METADATA
KolaViz-0.0.3.dist-info/WHEEL
KolaViz-0.0.3.dist-info/entry_points.txt
KolaViz-0.0.3.dist-info/top_level.txt
KolaViz-0.0.3.dist-info/RECORD
