Metadata-Version: 2.1
Name: KolaViz
Version: 0.0.3
Summary: Compute a collective dynamics from MOOC's discussion forums.
Home-page: https://git-lium.univ-lemans.fr/mkone/kola-indicator
Author: Malik Koné
Author-email: malik.kone.etu@univ-lemans.fr
License: UNKNOWN
Platform: UNKNOWN
Classifier: Development Status :: 4 - Beta
Classifier: Intended Audience :: Developers
Classifier: Intended Audience :: Education
Classifier: Intended Audience :: Science/Research
Classifier: License :: OSI Approved :: BSD License
Classifier: Natural Language :: French
Classifier: Natural Language :: English
Classifier: Operating System :: OS Independent
Classifier: Topic :: Education
Classifier: Topic :: Education :: Computer Aided Instruction (CAI)
Classifier: Topic :: Scientific/Engineering :: Information Analysis
Classifier: Topic :: Scientific/Engineering :: Visualization
Requires-Python: >=3.6
Requires-Dist: bs4
Requires-Dist: langdetect
Requires-Dist: matplotlib
Requires-Dist: nltk
Requires-Dist: numpy
Requires-Dist: pandas
Requires-Dist: scipy
Requires-Dist: sklearn
Requires-Dist: xkcdpass
Provides-Extra: rec
Requires-Dist: graph-tool ; extra == 'rec'
Requires-Dist: altair ; extra == 'rec'
Requires-Dist: hypothesis ; extra == 'rec'
